{
  "id":"default",
  "matchingType":"exact",
  "keywords": [
    {
        "words" : ["cat","chat","gato"],
        "fragment" : {
            "tags" : ["cats"]
        }
    },
    {
      "words" : ["dog","chien","perro"],
      "matchingType":"partial",
        "fragment" : {
          "path" : "OneFragmentForKeywordDog"
        }
    },
    {
      "words" : ["love","amour","aime","like"],
      "matchingType":"partial",
        "fragment" : {
          "path" : "OneFragmentForKeywordLove"
        }
    }
  ]
}
