{
  "Type": "Node",
  "Id": "MoreHappyKissOrGift",
  "Steps": [
    {
      "Type": "Text",
      "Label": {
        "en": "You feel happier when your partner gives you",
        "fr": "Tu es plus heureux quand la personne que tu aimes te donne",
        "es": "Eres m치s feliz cuando tu novio/novia te da"
      }
    }
  ],
  "Randomize": "true",
  "Commands": [
    {
      "Type": "Leaf",
      "Id": "MoreHappyKiss",
      "ElementValue": "1",
      "CommandLabel": {
        "en": "a kiss 游눎",
        "fr": "un bisou 游눎",
        "es": "un beso 游눎"
      },
      "Steps": [
        {
          "Type": "Action",
          "Name": "DoVote"
        },
        {
          "Type": "Action",
          "Name": "ShowSurveyResults"
        },
        {
          "Type": "AnimatedGif",
          "Parameters": {
            "Source": "Giphy",
            "Path": "AIDv87fiokBva"
          }
        }
      ]
    },
    {
      "Type": "Leaf",
      "Id": "MoreHappyGift",
      "ElementValue": "1",
      "CommandLabel": {
        "en": "a gift 游꾸",
        "fr": "un cadeau 游꾸",
        "es": "un regalo 游꾸"
      },
      "Steps": [
        {
          "Type": "Action",
          "Name": "DoVote"
        },
        {
          "Type": "Action",
          "Name": "ShowSurveyResults"
        },
        {
          "Type": "AnimatedGif",
          "Parameters": {
            "Source": "Giphy",
            "Path": "ANYZLuQ59mi64"
          }
        }
      ]
    }
  ]
}
