{
"Themes":
[
{ 
"Path" : "themes/emojiPandas",
"DefaultImage" : "themes/emojiPandas/small/shutterstock_431449828_8.jpg",
"SearchText" : "panda cartoon", 
"Labels":
  [
  {"Language":"fr-FR","Label":"Emoji Pandas"},
  {"Language":"en-EN","Label":"Emoji Pandas"},
  {"Language":"es-ES","Label":"Emoji Pandas"}
  ]
}
,
{ 
"Path" : "themes/horses",
"DefaultImage" : "themes/horses/small/shutterstock_173706239.jpg",
"Labels":
  [
  {"Language":"fr-FR","Label":"Chevaux"},
  {"Language":"en-EN","Label":"Horses"},
  {"Language":"es-ES","Label":"Caballos"}
  ]
}  
,
{ 
"Path" : "themes/animals",
"DefaultImage" : "themes/animals/small/iStock_000015359145_Large.jpg",
"Labels":
  [
  {"Language":"fr-FR","Label":"Animaux"},
  {"Language":"en-EN","Label":"Animals"},
  {"Language":"es-ES","Label":"Animales"}
  ]
}
, 
{ 
"Path" : "themes/strange",
"DefaultImage" : "themes/strange/small/310928_10150295389296564_166896605_n.jpg",
"SearchText" : "strange fun", 
"Labels":
  [
  {"Language":"fr-FR","Label":"Etrange"},
  {"Language":"en-EN","Label":"Weird"},
  {"Language":"es-ES","Label":"Extraño"}
  ]
}
,
{ 
"Path" : "themes/emoticons3",
"DefaultImage" : "themes/emoticons3/small/shutterstock_294472505_3.jpg",
"SearchText" : "smiley loop", 
"Labels":
  [
  {"Language":"fr-FR","Label":"Emoji II"},
  {"Language":"en-EN","Label":"Emoji II"},
  {"Language":"es-ES","Label":"Emoji II"}
  ]
} 

  
,
{ 
"Path" : "themes/football",
"DefaultImage" : "themes/football/small/shutterstock_75105484_1.jpg",
"SearchText" : "soccer", 
"Labels":
  [
  {"Language":"fr-FR","Label":"Football"},
  {"Language":"en-EN","Label":"Football"},
  {"Language":"es-ES","Label":"Fútbol"}
  ]
}
,
{ 
"Path" : "themes/emojiVarious",
"DefaultImage" : "cvd/intentions/default/xsmall/shutterstock_407290795_6.jpg",
"SearchText" : "emoji dance", 
"Labels":
  [
  {"Language":"fr-FR","Label":"Emoji Variés"},
  {"Language":"en-EN","Label":"Emoji Various"},
  {"Language":"es-ES","Label":"Emoji Vario"}
  ]
}  
,
{ 
"Path" : "themes/emojiGirlie",
"DefaultImage" : "cvd/intentions/default/xsmall/shutterstock_311548385_20.jpg",
"SearchText" : "smiley girly", 
"Labels":
  [
  {"Language":"fr-FR","Label":"Emoji Girlie"},
  {"Language":"en-EN","Label":"Emoji Girly"},
  {"Language":"es-ES","Label":"Emoji Girlie"}
  ]
}    
,
{ 
"Path" : "themes/pairs",
"DefaultImage" : "themes/pairs/small/shutterstock_139733785.jpg",
"SearchText" : "twins", 
"Labels":
  [
  {"Language":"fr-FR","Label":"Paires"},
  {"Language":"en-EN","Label":"Pairs"},
  {"Language":"es-ES","Label":"Pares"}
  ]
}  
]
}
