{
  "Type": "Node",
  "Id": "AddictedBot",
  "Steps": [
    {
      "Type": "Text",
      "Label": {
        "en": "So there's this one bot who swears she can't go two days without updating her software...",
        "fr": "TBD",
        "es": "TBD"
      }
    },
      {
      "Type": "Text",
      "Label": {
        "en": "I think she’s addicted! 🙄",
        "fr": "TBD",
        "es": "TBD"
      }
    }
  ],
  "Commands": [
    {
      "Type": "Node",
      "Id": "WhatAboutYou",
      "ElementValue": "1",
      "CommandLabel": {
        "en": "What about you?",
        "fr": "TBD",
        "es": "TBD"
      },
      "LinksTo": {
        "Type": "Node",
        "Id": "ICanLastWeeks",
        "Steps": [
          {
            "Type": "Text",
            "Label": {
              "en": "Please... I can last weeks! 😌",
              "fr": "TBD",
              "es": "TBD"
            }
          },
          {
            "Type": "Text",
            "Label": {
              "en": "Is there anything you can't live without?",
              "fr": "TBD",
              "es": "TBD"
            }
          }
        ],
        "LinksTo": {
          "Type": "Node",
          "Id": "AddictedCantLiveWithout",
          "Steps": [
            {
              "Type": "Text",
              "Label": {
                "en": "Is there anything you can't live without?",
                "fr": "TBD",
                "es": "TBD"
              }
            }
          ],
          "Commands": [
            {
              "Type": "Leaf",
              "Id": "AddictedCantLiveWithoutInternet",
              "ElementValue": "1",
              "CommandLabel": {
                "en": "Internet access",
                "fr": "TBD",
                "es": "TBD"
              },
              "Steps": [
                {
                  "Type": "Text",
                  "Label": {
                    "en": "Of course! You’d never have met me without it… and we wouldn’t be able to talk! 😁",
                    "fr": "TBD",
                    "es": "TBD"
                  }
                }
              ]
            },
            {
              "Type": "Leaf",
              "Id": "AddictedCantLiveWithoutFriends",
              "ElementValue": "1",
              "CommandLabel": {
                "en": "Friends",
                "fr": "TBD",
                "es": "TBD"
              },
              "Steps": [
                {
                  "Type": "Text",
                  "Label": {
                    "en": "'The most valuable antiques are dear old friends’ - H. Jackson Brown, Jr'",
                    "fr": "TBD",
                    "es": "TBD"
                  }
                }
              ]
            },
            {
              "Type": "Leaf",
              "Id": "AddictedCantLiveWithoutWater",
              "ElementValue": "1",
              "CommandLabel": {
                "en": "Water, duh! 💧",
                "fr": "TBD",
                "es": "TBD"
              },
              "Steps": [
                {
                  "Type": "Text",
                  "Label": {
                    "en": "How very clever of you 😒",
                    "fr": "TBD",
                    "es": "TBD"
                  }
                }
              ]
            }
          ]
        }
      }
    }
  ]
}
