
{
  "Type": "Question",
  "Id": "LiveInChinaOrRussia",
  "Label":
    {
      "en": "Would you rather live in",
      "fr": "Tu préférerais vivre en",
      "es": "Preferías vivir en"
    }
  ,
  "Randomize": "true",
  "Commands":
      [
        {
          "Type": "Survey",
          "Id": "LiveInChina",
          "StepValue" : "1",
          "OptionalFeedback": {
            "Type": "AnimatedGif",
            "Source": "Giphy",
            "Path": "26uTsjWlTRFxIJHm8"
          },
          "Label":{
            "en": "China",
            "fr": "Chine",
            "es": "China"
          }
        }
        ,
        {
          "Type": "Survey",
          "Id": "LiveInRussia",
          "StepValue" : "1",
          "OptionalFeedback": {
            "Type": "AnimatedGif",
            "Source": "Giphy",
            "Path": "s96520HbKjBfy"
          },
          "Label":{
            "en": "Russia",
            "fr": "Russie",
            "es": "Rusia"
          }
        }
      ]
}

