
{
  "Type": "Question",
  "Id": "WouldYouRatherLiveinNAmericaorEurope",
  "Label":
    {
      "en": "Would you rather live in",
      "fr": "Tu préférerais vivre en",
      "es": "Preferirías vivir en"
    }
  ,
  "Randomize": "true",
  "Commands":
      [
        {
          "Type": "Survey",
          "Id": "LiveInNorthAmerica",
          "StepValue" : "1",
          "OptionalFeedback": {
            "Type": "AnimatedGif",
            "Source": "Giphy",
            "Path": "oobNzX5ICcRZC"
          },
          "Label":{
            "en": "North America",
            "fr": "Amérique du Nord",
            "es": "América del Norte"
          }
        }
        ,
        {
          "Type": "Survey",
          "Id": "LiveInEurope",
          "StepValue" : "1",
          "OptionalFeedback": {
            "Type": "AnimatedGif",
            "Source": "Giphy",
            "Path": "tIeCLkB8geYtW"
          },
          "Label":{
            "en": "Europe",
            "fr": "Europe",
            "es": "Europa"
          }
        }
      ]
}

